stockmarketsearch/__init__.py
stockmarketsearch/africanmarkets.py
stockmarketsearch/main.py
stockmarketsearch/nginvesting.py
stockmarketsearch/webdriver.py
stockmarketsearch/yahoofinance.py
stockmarketsearch-0.2.4.dist-info/licenses/LICENSE
stockmarketsearch-0.2.4.dist-info/METADATA
stockmarketsearch-0.2.4.dist-info/WHEEL
stockmarketsearch-0.2.4.dist-info/top_level.txt
stockmarketsearch-0.2.4.dist-info/RECORD
