Metadata-Version: 2.4
Name: stockmarketsearch
Version: 0.2.4
Summary: A package for searching stock information across multiple sources.
Home-page: https://github.com/ininike/stockmarketsearch
Author: Inioluwa Adenaike
Author-email: inioluwadenaike@gmail.com
License: MIT
Classifier: Programming Language :: Python :: 3
Classifier: Operating System :: OS Independent
License-File: LICENSE
Requires-Dist: asyncio
Requires-Dist: requests
Requires-Dist: beautifulsoup4
Requires-Dist: selenium
Requires-Dist: tzdata
Dynamic: license-file
